factly/standard_names/__init__.py
factly/standard_names/airline.py
factly/standard_names/banks.py
factly/standard_names/cities.py
factly/standard_names/country.py
factly/standard_names/crops.py
factly/standard_names/district.py
factly/standard_names/enums.py
factly/standard_names/settings.py
factly/standard_names/standardise_data.py
factly/standard_names/states.py
factly/standard_names/units.py
factly/standard_names/utils.py
factly_standard_names-0.2.4.dist-info/METADATA
factly_standard_names-0.2.4.dist-info/WHEEL
factly_standard_names-0.2.4.dist-info/RECORD
