Metadata-Version: 2.4
Name: factly-standard-names
Version: 0.2.4
Summary: 
Author: Factly Labs
Requires-Python: >=3.9,<4.0
Classifier: Programming Language :: Python :: 3
Classifier: Programming Language :: Python :: 3.9
Classifier: Programming Language :: Python :: 3.10
Classifier: Programming Language :: Python :: 3.11
Classifier: Programming Language :: Python :: 3.12
Classifier: Programming Language :: Python :: 3.13
Classifier: Programming Language :: Python :: 3.14
Requires-Dist: fuzzywuzzy (>=0.18.0,<0.19.0)
Requires-Dist: pandas (>=2.0.0,<3.0.0)
Requires-Dist: tenacity (>=9.1.2,<10.0.0)
